{
    "0.05": {
        "mean_size": 1.0961,
        "q": 0.7443240880966187,
        "0": "{6}",
        "1": "{0, 2}",
        "2": "{4, 9}",
        "3": "{4, 9}",
        "4": "{7, 9}",
        "5": "{4, 9}",
        "6": "{4, 9}",
        "7": "{4, 9}"
    },
    "0.1": {
        "mean_size": 0.9324,
        "q": 0.5594450235366821,
        "0": "{6}",
        "1": "{}",
        "2": "{9}",
        "3": "{9}",
        "4": "{7}",
        "5": "{9}",
        "6": "{4, 9}",
        "7": "{9}"
    },
    "0.15": {
        "mean_size": 0.8427,
        "q": 0.42762261629104614,
        "0": "{}",
        "1": "{}",
        "2": "{}",
        "3": "{9}",
        "4": "{7}",
        "5": "{9}",
        "6": "{}",
        "7": "{}"
    },
    "0.2": {
        "mean_size": 0.7689,
        "q": 0.33762645721435547,
        "0": "{}",
        "1": "{}",
        "2": "{}",
        "3": "{}",
        "4": "{}",
        "5": "{}",
        "6": "{}",
        "7": "{}"
    },
    "0.25": {
        "mean_size": 0.7061,
        "q": 0.2737169861793518,
        "0": "{}",
        "1": "{}",
        "2": "{}",
        "3": "{}",
        "4": "{}",
        "5": "{}",
        "6": "{}",
        "7": "{}"
    },
    "0.3": {
        "mean_size": 0.6546,
        "q": 0.23265141248703003,
        "0": "{}",
        "1": "{}",
        "2": "{}",
        "3": "{}",
        "4": "{}",
        "5": "{}",
        "6": "{}",
        "7": "{}"
    },
    "0.35": {
        "mean_size": 0.5939,
        "q": 0.1950252652168274,
        "0": "{}",
        "1": "{}",
        "2": "{}",
        "3": "{}",
        "4": "{}",
        "5": "{}",
        "6": "{}",
        "7": "{}"
    },
    "0.4": {
        "mean_size": 0.5488,
        "q": 0.1714072823524475,
        "0": "{}",
        "1": "{}",
        "2": "{}",
        "3": "{}",
        "4": "{}",
        "5": "{}",
        "6": "{}",
        "7": "{}"
    },
    "0.45": {
        "mean_size": 0.4842,
        "q": 0.14650654792785645,
        "0": "{}",
        "1": "{}",
        "2": "{}",
        "3": "{}",
        "4": "{}",
        "5": "{}",
        "6": "{}",
        "7": "{}"
    },
    "0.5": {
        "mean_size": 0.4319,
        "q": 0.12829113006591797,
        "0": "{}",
        "1": "{}",
        "2": "{}",
        "3": "{}",
        "4": "{}",
        "5": "{}",
        "6": "{}",
        "7": "{}"
    },
    "0.55": {
        "mean_size": 0.3837,
        "q": 0.11269491910934448,
        "0": "{}",
        "1": "{}",
        "2": "{}",
        "3": "{}",
        "4": "{}",
        "5": "{}",
        "6": "{}",
        "7": "{}"
    },
    "0.6": {
        "mean_size": 0.3378,
        "q": 0.10012447834014893,
        "0": "{}",
        "1": "{}",
        "2": "{}",
        "3": "{}",
        "4": "{}",
        "5": "{}",
        "6": "{}",
        "7": "{}"
    },
    "0.65": {
        "mean_size": 0.2913,
        "q": 0.08861374855041504,
        "0": "{}",
        "1": "{}",
        "2": "{}",
        "3": "{}",
        "4": "{}",
        "5": "{}",
        "6": "{}",
        "7": "{}"
    },
    "0.7": {
        "mean_size": 0.2491,
        "q": 0.07845455408096313,
        "0": "{}",
        "1": "{}",
        "2": "{}",
        "3": "{}",
        "4": "{}",
        "5": "{}",
        "6": "{}",
        "7": "{}"
    },
    "0.75": {
        "mean_size": 0.2061,
        "q": 0.06915640830993652,
        "0": "{}",
        "1": "{}",
        "2": "{}",
        "3": "{}",
        "4": "{}",
        "5": "{}",
        "6": "{}",
        "7": "{}"
    },
    "0.8": {
        "mean_size": 0.1653,
        "q": 0.06095230579376221,
        "0": "{}",
        "1": "{}",
        "2": "{}",
        "3": "{}",
        "4": "{}",
        "5": "{}",
        "6": "{}",
        "7": "{}"
    },
    "0.85": {
        "mean_size": 0.122,
        "q": 0.05304056406021118,
        "0": "{}",
        "1": "{}",
        "2": "{}",
        "3": "{}",
        "4": "{}",
        "5": "{}",
        "6": "{}",
        "7": "{}"
    },
    "0.9": {
        "mean_size": 0.0775,
        "q": 0.04563063383102417,
        "0": "{}",
        "1": "{}",
        "2": "{}",
        "3": "{}",
        "4": "{}",
        "5": "{}",
        "6": "{}",
        "7": "{}"
    },
    "0.95": {
        "mean_size": 0.0396,
        "q": 0.03805011510848999,
        "0": "{}",
        "1": "{}",
        "2": "{}",
        "3": "{}",
        "4": "{}",
        "5": "{}",
        "6": "{}",
        "7": "{}"
    },
    "0.037000000000000005": {
        "mean_size": 1.2147,
        "q": 0.8180860877037048,
        "0": "{6}",
        "1": "{0, 2, 5}",
        "2": "{4, 9}",
        "3": "{4, 9}",
        "4": "{7, 9}",
        "5": "{4, 9}",
        "6": "{4, 9}",
        "7": "{4, 9}"
    }
}